{"title":"二次元杂货铺","slug":"anime-history","date":"2037-10-01T10:26:16.000Z","updated":"2018-01-19T05:48:34.844Z","comments":true,"excerpt":"","content":"<p>这是我的一个公众号，主题是 ACG 发展史和周边资讯。求关注~</p>\n<h3 id=\"茶太与兔子蘑菇\"><a href=\"#茶太与兔子蘑菇\" class=\"headerlink\" title=\"茶太与兔子蘑菇\"></a><a href=\"http://url.cn/5fbUwFi\" target=\"_blank\" rel=\"external\">茶太与兔子蘑菇</a></h3><p>同人歌姬茶太太，发布于 17/10/30</p>\n<h3 id=\"凉宫春日与谷川流的消失\"><a href=\"#凉宫春日与谷川流的消失\" class=\"headerlink\" title=\"凉宫春日与谷川流的消失\"></a><a href=\"http://url.cn/5s6NgKH\" target=\"_blank\" rel=\"external\">凉宫春日与谷川流的消失</a></h3><p>凉宫春日的忧郁系列，发布于 17/12/4</p>\n","categories":[],"tags":[{"name":"ACG","path":"api/tags/ACG.json"}]}